.gitignore
.gitlab-ci.yml
README.md
setup.py
bin/CVMFSDevChecker
bin/CVMFSDevEnvKitInstaller
bin/CVMFSDevGC
bin/CVMFSDevManager
bin/CVMFSGitConDDBSync
bin/CVMFSGitCondDBCvmfsGc
bin/CVMFSGitCondDBGitGc
bin/CVMFSGitMirrors
bin/CVMFSNightliesINstallTimePlotter
bin/CVMFSNightliesInstall
bin/CVMFSNightliesInstallByProject
bin/CVMFSNightliesRemove
bin/CVMFSNightliesRemoveLinks
bin/CVMFSPlotStats
bin/CVMFSTransactionWrapper
bin/LocalNightiliesInstall
bin/SampleClient
lbCVMFSTools/.coverage
lbCVMFSTools/Audit.py
lbCVMFSTools/GenericClient.py
lbCVMFSTools/Injector.py
lbCVMFSTools/Scheduler.py
lbCVMFSTools/TaskHandlerInterface.py
lbCVMFSTools/TransactionHandlerInterface.py
lbCVMFSTools/__init__.py
lbCVMFSTools/nosetests.xml
lbCVMFSTools.egg-info/PKG-INFO
lbCVMFSTools.egg-info/SOURCES.txt
lbCVMFSTools.egg-info/dependency_links.txt
lbCVMFSTools.egg-info/requires.txt
lbCVMFSTools.egg-info/top_level.txt
lbCVMFSTools/TaskHandlers/__init__.py
lbCVMFSTools/TaskHandlers/DevPackagesGC/DevPackagesGC.py
lbCVMFSTools/TaskHandlers/DevPackagesGC/__init__.py
lbCVMFSTools/TaskHandlers/DevPackagesInstaller/.___init__.py
lbCVMFSTools/TaskHandlers/DevPackagesInstaller/DevPackagesInstaller.py
lbCVMFSTools/TaskHandlers/DevPackagesInstaller/__init__.py
lbCVMFSTools/TaskHandlers/DevPackagesInstaller/tests/TestDevPackages.py
lbCVMFSTools/TaskHandlers/DevPackagesInstaller/tests/__init__.py
lbCVMFSTools/TaskHandlers/EnvKitInstaller/EnvKitInstaller.py
lbCVMFSTools/TaskHandlers/EnvKitInstaller/__init__.py
lbCVMFSTools/TaskHandlers/EnvKitInstaller/tests/TestEnvKitInstaller.py
lbCVMFSTools/TaskHandlers/EnvKitInstaller/tests/__init__.py
lbCVMFSTools/TaskHandlers/GITCONDDBCvmfsGC/GITCONDDBCvmfsGC.py
lbCVMFSTools/TaskHandlers/GITCONDDBCvmfsGC/__init__.py
lbCVMFSTools/TaskHandlers/GITCONDDBGitGc/GITCONDDBGitGc.py
lbCVMFSTools/TaskHandlers/GITCONDDBGitGc/__init__.py
lbCVMFSTools/TaskHandlers/GITCONDDBSync/GITCONDDBSync.py
lbCVMFSTools/TaskHandlers/GITCONDDBSync/__init__.py
lbCVMFSTools/TaskHandlers/GitMirrorTask/GitMirrorTask.py
lbCVMFSTools/TaskHandlers/GitMirrorTask/__init__.py
lbCVMFSTools/TaskHandlers/GitMirrorTask/tests/TestGitMirror.py
