Metadata-Version: 1.1
Name: lbCVMFSTools
Version: 1.2.9
Summary: LHCb CVMFS-Stratum0 tool-set
Home-page: https://gitlab.cern.ch/lhcb-core/LbCVMFSTools
Author: CERN - LHCb Core Software
Author-email: lhcb-core-soft@cern.ch
License: GPL
Keywords: LHCb
Platform: UNKNOWN
Classifier: Development Status :: 3 - Alpha
Classifier: License :: OSI Approved :: GNU General Public License v3 (GPLv3)
Classifier: Programming Language :: Python :: 2.6
Classifier: Programming Language :: Python :: 2.7
Classifier: Programming Language :: Python :: 3.5
